vivre/__init__.py
vivre/__main__.py
vivre/align.py
vivre/api.py
vivre/cli.py
vivre/format.py
vivre/integration.py
vivre/parser.py
vivre/segmenter.py
vivre-0.1.0.dist-info/LICENSE
vivre-0.1.0.dist-info/METADATA
vivre-0.1.0.dist-info/WHEEL
vivre-0.1.0.dist-info/entry_points.txt
vivre-0.1.0.dist-info/RECORD
