Metadata-Version: 2.3
Name: vivre
Version: 0.1.0
Summary: A Python library for machine learning and corpus linguistics
Author: Aniket Dixit
Author-email: aniketdixit00.ani@gmail.com
Requires-Python: >=3.11,<3.14
Classifier: Programming Language :: Python :: 3
Classifier: Programming Language :: Python :: 3.11
Classifier: Programming Language :: Python :: 3.12
Classifier: Programming Language :: Python :: 3.13
Requires-Dist: beautifulsoup4 (>=4.13.4,<5.0.0)
Requires-Dist: defusedxml (>=0.7.1,<0.8.0)
Requires-Dist: ebooklib (>=0.19,<0.20)
Requires-Dist: langdetect (>=1.0.9,<2.0.0)
Requires-Dist: lxml (>=6.0.0,<7.0.0)
Requires-Dist: nltk (>=3.9.1,<4.0.0)
Requires-Dist: numpy (>=2.3.1,<3.0.0)
Requires-Dist: requests (>=2.32.4,<3.0.0)
Requires-Dist: rich (>=14.0.0,<15.0.0)
Requires-Dist: scipy (>=1.16.0,<2.0.0)
Requires-Dist: spacy (>=3.8.7,<4.0.0)
Requires-Dist: typer (>=0.16.0,<0.17.0)
